MANIFEST.in
README.rst
setup.py
MetricsLog.egg-info/PKG-INFO
MetricsLog.egg-info/SOURCES.txt
MetricsLog.egg-info/dependency_links.txt
MetricsLog.egg-info/top_level.txt
metricslog/__init__.py
metricslog/collector.py
metricslog/compat.py
metricslog/manager.py
metricslog/types.py
metricslog/ext/__init__.py
metricslog/ext/_colors.py
metricslog/ext/formatter.py
metricslog/ext/logstash.py