Metadata-Version: 1.0
Name: MetricsLog
Version: 0.1.3
Summary: Send metrics as structured logs
Home-page: https://github.com/vmagamedov/metricslog
Author: Vladimir Magamedov
Author-email: vladimir@magamedov.com
License: BSD
Platform: UNKNOWN
